{"is_source_file": true, "format": "json", "description": ".json file: project.json", "external_files": [], "external_methods": [], "published": [], "classes": [], "methods": [], "calls": [], "search-terms": ["project.json", "json"], "state": 2, "filename": "src/assets/data/project.json", "format-version": 4, "code-base-name": "https://github.com/DarssiniRamesh/jira-clone-angular.git:master", "knowledge_revision": 208, "git_revision": "38d77821208da60e1b879947084a3e0e366afc8f", "revision_history": [{"208": "38d77821208da60e1b879947084a3e0e366afc8f"}, {"208": "38d77821208da60e1b879947084a3e0e366afc8f"}], "file_id": 129}